Workbook
Name Configuracióndeempresa_Abreviaturademoneda: INDEX('Configuración de empresa'!$C$3:$C$20,MATCH("Abreviatura de moneda",'Configuración de empresa'!$B$3:$B$20,0))
Name Configuracióndeempresa_Beneficiariodelcheque: INDEX('Configuración de empresa'!$C$3:$C$20,MATCH("Emita los cheques a nombre de",'Configuración de empresa'!$B$3:$B$20,0))
Name Configuracióndeempresa_Correoelectrónico: INDEX('Configuración de empresa'!$C$3:$C$20,MATCH("Correo electrónico",'Configuración de empresa'!$B$3:$B$20,0))
Name Configuracióndeempresa_Cuentabancaria: INDEX('Configuración de empresa'!$C$3:$C$20,MATCH("Número de cuenta",'Configuración de empresa'!$B$3:$B$20,0))
Name Configuracióndeempresa_Direcciónbancaria: INDEX('Configuración de empresa'!$C$3:$C$20,MATCH("Dirección del banco",'Configuración de empresa'!$B$3:$B$20,0))
Name Configuracióndeempresa_DirecciónLínea1: INDEX('Configuración de empresa'!$C$3:$C$20,MATCH("Dirección - Línea 1",'Configuración de empresa'!$B$3:$B$20,0))
Name Configuracióndeempresa_DirecciónLínea2: INDEX('Configuración de empresa'!$C$3:$C$20,MATCH("Dirección - Línea 2",'Configuración de empresa'!$B$3:$B$20,0))
Name Configuracióndeempresa_DirecciónLínea3: INDEX('Configuración de empresa'!$C$3:$C$20,MATCH("Dirección - Línea 3",'Configuración de empresa'!$B$3:$B$20,0))
Name Configuracióndeempresa_DirecciónLínea4: INDEX('Configuración de empresa'!$C$3:$C$20,MATCH("Dirección - Línea 4",'Configuración de empresa'!$B$3:$B$20,0))
Name Configuracióndeempresa_DirecciónLínea5: INDEX('Configuración de empresa'!$C$3:$C$20,MATCH("Dirección - Línea 5",'Configuración de empresa'!$B$3:$B$20,0))
Name Configuracióndeempresa_DirecciónURL: INDEX('Configuración de empresa'!$C$3:$C$20,MATCH("Sitio web",'Configuración de empresa'!$B$3:$B$20,0))
Name Configuracióndeempresa_IdentificacióndelBanco: INDEX('Configuración de empresa'!$C$3:$C$20,MATCH("Número de identificación del banco (código SWIFT)",'Configuración de empresa'!$B$3:$B$20,0))
Name Configuracióndeempresa_Nombredelacompañía: INDEX('Configuración de empresa'!$C$3:$C$20,MATCH("Nombre de la compañía",'Configuración de empresa'!$B$3:$B$20,0))
Name Configuracióndeempresa_Nombredelbanco: INDEX('Configuración de empresa'!$C$3:$C$20,MATCH("Nombre del banco",'Configuración de empresa'!$B$3:$B$20,0))
Name Configuracióndeempresa_NombredelBancoBeneficiario: INDEX('Configuración de empresa'!$C$3:$C$20,MATCH("Nombre del beneficiario de la transferencia bancaria",'Configuración de empresa'!$B$3:$B$20,0))
Name Configuracióndeempresa_Sufax: INDEX('Configuración de empresa'!$C$3:$C$20,MATCH("Facsímile",'Configuración de empresa'!$B$3:$B$20,0))
Name Configuracióndeempresa_Sunombre: INDEX('Configuración de empresa'!$C$3:$C$20,MATCH("Su nombre",'Configuración de empresa'!$B$3:$B$20,0))
Name Configuracióndeempresa_Teléfono: INDEX('Configuración de empresa'!$C$3:$C$20,MATCH("Teléfono",'Configuración de empresa'!$B$3:$B$20,0))
Name Totalfactura: Factura!$E$33
Name Visualizacióndelnúmerodefactura: Factura!$C$2

Sheet Factura
B2: FACTURA | C2: 15
B3: =TODAY() -> 46001 | D3: =Totalfactura -> 0
B4: ="VENCIMIENTO DEL PAGO: "&TEXT(B3+30,"dd Mmmm aaaa") -> VENCIMIENTO DEL PAGO: 09 enero viernes
B6: CECILIA CORNEJO | D6: ='Configuración de empresa'!C4 -> ADVENTURE WORKS
B7: Fabrikam, Inc. | D7: ='Configuración de empresa'!C5 -> 23456 Maple Street
D8: ='Configuración de empresa'!C6 -> Orange Grove, CA 09876
E9: 0
E10: =Configuracióndeempresa_DirecciónLínea4 -> 0
B14: CANTIDAD | C14: DETALLES | D14: PRECIO UNITARIO | E14: TOTAL DE LÍNEA
B15: 1 | E15: =IFERROR(Factura!$D15*Factura!$B15,"") -> 0
E16: =IFERROR(Factura!$D16*Factura!$B16,"") -> 0
E17: =IFERROR(Factura!$D17*Factura!$B17,"") -> 0
E18: =IFERROR(Factura!$D18*Factura!$B18,"") -> 0
E19: =IFERROR(Factura!$D19*Factura!$B19,"") -> 0
E20: =IFERROR(Factura!$D20*Factura!$B20,"") -> 0
E21: =IFERROR(Factura!$D21*Factura!$B21,"") -> 0
E22: =IFERROR(Factura!$D22*Factura!$B22,"") -> 0
E23: =IFERROR(Factura!$D23*Factura!$B23,"") -> 0
E24: =IFERROR(Factura!$D24*Factura!$B24,"") -> 0
E25: =IFERROR(Factura!$D25*Factura!$B25,"") -> 0
E26: =IFERROR(Factura!$D26*Factura!$B26,"") -> 0
E27: =IFERROR(Factura!$D27*Factura!$B27,"") -> 0
... E29: =IFERROR(Factura!$D29*Factura!$B29,"") -> 0
D30: Descuento
D31: Total neto | E31: =SUM(Factura!$E$15:$E$29)-E30 -> 0
D32: Impuesto
D33: =REPT(Configuracióndeempresa_Abreviaturademoneda,LEN(Configuracióndeempresa_Abreviaturademoneda)>0) & " TOTAL" -> USD TOTAL | E33: =E31+E32 -> 0
B36: DETALLES DEL PAGO | E36: INFORMACIÓN ADICIONAL
B37: ="Nombre del beneficiario " & Configuracióndeempresa_NombredelBancoBeneficiario -> Nombre del beneficiario Adventure Works | E37: =IFERROR(Configuracióndeempresa_Sunombre,"") -> Enrique Gil
B38: ="Nombre del banco: " & Configuracióndeempresa_Nombredelbanco -> Nombre del banco: Woodgrove Bank | E38: =IFERROR("Teléfono: " & Configuracióndeempresa_Teléfono,"")
B39: ="Dirección del banco: " & Configuracióndeempresa_Direcciónbancaria -> Dirección del banco: 234 Main St. Orange Grove, CA 09876 | E39: =IFERROR("Facsimile: " & Configuracióndeempresa_Sufax,"")
B40: ="Número de cuenta " & Configuracióndeempresa_Cuentabancaria -> Número de cuenta 1234567 | E40: =IFERROR(Configuracióndeempresa_DirecciónURL,"") -> Adventure-Works.com
B41: ="Número de identificación del banco (código SWIFT) " & 'Configuración de empresa'!C19 -> Número de identificación del banco (código SWIFT) 9876543210 | E41: =IFERROR(Configuracióndeempresa_Correoelectrónico,"") -> Accounting@Adventure-Works.com
B42: ="Referencia de pago " & Visualizacióndelnúmerodefactura -> Referencia de pago 15 | E42: =IFERROR(IF(LEN(Client_PO),"Contract/PO: " & Client_PO,""),"")
B44: =UPPER("El pago debe realizarse por transferencia bancaria o mediante un cheque a nombre de " & Configuracióndeempresa_Beneficiariodelcheque & ".") -> EL PAGO DEBE REALIZARSE POR TRANSFERENCIA BANCARIA O MEDIANTE UN CHEQUE A NOMBRE DE ADVENTURE WORKS.

Sheet Configuración de empresa
B1: CONFIGURACIÓN DE LA EMPRESA
B2: DATOS SOBRE SU EMPRESA | C2: VALOR
B3: Su nombre | C3: Enrique Gil
B4: Nombre de la compañía | C4: ADVENTURE WORKS
B5: Dirección - Línea 1 | C5: 23456 Maple Street
B6: Dirección - Línea 2 | C6: Orange Grove, CA 09876
B7: Dirección - Línea 3
B8: Dirección - Línea 4
B9: Dirección - Línea 5
B10: Consecutivo
B11: Celular
B12: Sitio web | C12: Adventure-Works.com
B13: Correo electrónico | C13: Accounting@Adventure-Works.com
B14: Abreviatura de moneda | C14: USD
B15: Nombre del beneficiario de la transferencia bancaria | C15: Adventure Works
B16: Nombre del banco | C16: Woodgrove Bank
B17: Dirección del banco | C17: 234 Main St. Orange Grove, CA 09876
B18: Número de cuenta | C18: 1234567
B19: Número de identificación del banco (CLABE Interbancaria) | C19: 9876543210
B20: Emita los cheques a nombre de | C20: Adventure Works
